pyfmto/__init__.py
pyfmto/core/__init__.py
pyfmto/core/component.py
pyfmto/core/typing.py
pyfmto/experiment/__init__.py
pyfmto/experiment/config.py
pyfmto/experiment/launcher.py
pyfmto/experiment/reporter.py
pyfmto/experiment/utils.py
pyfmto/framework/__init__.py
pyfmto/framework/client.py
pyfmto/framework/packages.py
pyfmto/framework/server.py
pyfmto/problem/__init__.py
pyfmto/problem/problem.py
pyfmto/problem/solution.py
pyfmto/utilities/__init__.py
pyfmto/utilities/cli.py
pyfmto/utilities/io.py
pyfmto/utilities/loaders.py
pyfmto/utilities/loggers.py
pyfmto/utilities/schemas.py
pyfmto/utilities/tools.py
pyfmto-0.3.2.dist-info/licenses/LICENSE
pyfmto-0.3.2.dist-info/METADATA
pyfmto-0.3.2.dist-info/WHEEL
pyfmto-0.3.2.dist-info/entry_points.txt
pyfmto-0.3.2.dist-info/top_level.txt
pyfmto-0.3.2.dist-info/RECORD
