Metadata-Version: 2.4
Name: pyfmto
Version: 0.3.2
Summary: A Python library for federated many-task optimization research
Author-email: Xiaoxu Zhang <xxzhang_official@163.com>
Project-URL: Homepage, https://github.com/Xiaoxu-Zhang/pyfmto
Classifier: Development Status :: 4 - Beta
Classifier: Programming Language :: Python
Classifier: Programming Language :: Python :: 3
Classifier: Programming Language :: Python :: 3.9
Classifier: Programming Language :: Python :: 3.10
Classifier: Programming Language :: Python :: 3.11
Classifier: Programming Language :: Python :: 3.12
Classifier: Programming Language :: Python :: 3.13
Classifier: Intended Audience :: Science/Research
Classifier: Intended Audience :: Education
Classifier: Topic :: Scientific/Engineering
Classifier: Topic :: Scientific/Engineering :: Artificial Intelligence
Classifier: Operating System :: OS Independent
Classifier: Operating System :: POSIX :: Linux
Classifier: Operating System :: MacOS :: MacOS X
Classifier: Operating System :: Microsoft :: Windows
Requires-Python: >=3.9
License-File: LICENSE
Requires-Dist: fastapi
Requires-Dist: jinja2
Requires-Dist: matplotlib
Requires-Dist: msgpack
Requires-Dist: numpy
Requires-Dist: openpyxl
Requires-Dist: opfunu
Requires-Dist: pandas
Requires-Dist: pillow
Requires-Dist: pydantic
Requires-Dist: pydantic_core
Requires-Dist: pyDOE
Requires-Dist: pyvista
Requires-Dist: pyyaml
Requires-Dist: requests
Requires-Dist: ruamel-yaml
Requires-Dist: scienceplots
Requires-Dist: scikit-learn
Requires-Dist: scipy
Requires-Dist: seaborn
Requires-Dist: setproctitle
Requires-Dist: tabulate
Requires-Dist: tqdm
Requires-Dist: uvicorn
Requires-Dist: wrapt
Requires-Dist: rich
Requires-Dist: deepdiff
Requires-Dist: psutil
Requires-Dist: concurrent_log_handler
Provides-Extra: dev
Requires-Dist: build; extra == "dev"
Requires-Dist: pyproject_hooks; extra == "dev"
Requires-Dist: setuptools; extra == "dev"
Requires-Dist: coverage; extra == "dev"
Requires-Dist: pytest; extra == "dev"
Requires-Dist: pytest-cov; extra == "dev"
Requires-Dist: pytest-env; extra == "dev"
Requires-Dist: iniconfig; extra == "dev"
Requires-Dist: ruff; extra == "dev"
Requires-Dist: mypy; extra == "dev"
Requires-Dist: mypy_extensions; extra == "dev"
Requires-Dist: types-PyYAML; extra == "dev"
Requires-Dist: types-tabulate; extra == "dev"
Requires-Dist: types-requests; extra == "dev"
Requires-Dist: typing-inspection; extra == "dev"
Requires-Dist: typing_extensions; extra == "dev"
Dynamic: license-file
